email_from_template/__init__.py
email_from_template/app_settings.py
email_from_template/context_processors.py
email_from_template/send_mail.py
email_from_template/templates/email_from_template/body.email
email_from_template/templates/email_from_template/html.email
email_from_template/templates/email_from_template/subject.email
django_email_from_template-2.4.1.dist-info/COPYING
django_email_from_template-2.4.1.dist-info/METADATA
django_email_from_template-2.4.1.dist-info/WHEEL
django_email_from_template-2.4.1.dist-info/top_level.txt
django_email_from_template-2.4.1.dist-info/RECORD
