Metadata-Version: 2.1
Name: django-email-from-template
Version: 2.4.1
Summary: Send emails generated entirely from Django templates.
Home-page: https://chris-lamb.co.uk/projects/django-email-from-template
Author: Chris Lamb
Author-email: chris@chris-lamb.co.uk
License: BSD
Platform: UNKNOWN
Requires-Dist: Django (>=1.8)
